topik/__init__.py
topik/_version.py
topik/singleton_registry.py
topik/fileio/__init__.py
topik/fileio/_registry.py
topik/fileio/base_output.py
topik/fileio/in_document_folder.py
topik/fileio/in_elastic.py
topik/fileio/in_json.py
topik/fileio/out_elastic.py
topik/fileio/out_memory.py
topik/fileio/project.py
topik/fileio/reader.py
topik/fileio/tests/__init__.py
topik/fileio/tests/_solutions.py
topik/fileio/tests/test_in_document_folder.py
topik/fileio/tests/test_in_elastic.py
topik/fileio/tests/test_in_json.py
topik/fileio/tests/test_outputs.py
topik/fileio/tests/test_project.py
topik/fileio/tests/test_reader.py
topik/models/__init__.py
topik/models/_registry.py
topik/models/base_model_output.py
topik/models/lda.py
topik/models/plsa.py
topik/models/tests/__init__.py
topik/models/tests/test_data.py
topik/models/tests/test_lda.py
topik/models/tests/test_plsa.py
topik/simple_run/__init__.py
topik/simple_run/cli.py
topik/simple_run/run.py
topik/simple_run/tests/__init__.py
topik/simple_run/tests/test_run_api.py
topik/tokenizers/__init__.py
topik/tokenizers/_registry.py
topik/tokenizers/entities.py
topik/tokenizers/ngrams.py
topik/tokenizers/simple.py
topik/tokenizers/tests/__init__.py
topik/tokenizers/tests/test_entities.py
topik/tokenizers/tests/test_ngrams.py
topik/tokenizers/tests/test_simple.py
topik/transformers/__init__.py
topik/transformers/_registry.py
topik/vectorizers/__init__.py
topik/vectorizers/_registry.py
topik/vectorizers/bag_of_words.py
topik/vectorizers/tfidf.py
topik/vectorizers/vectorizer_output.py
topik/vectorizers/tests/__init__.py
topik/vectorizers/tests/test_bag_of_words.py
topik/vectorizers/tests/test_output.py
topik/vectorizers/tests/test_tfidf.py
topik/visualizers/__init__.py
topik/visualizers/_registry.py
topik/visualizers/data_formatters.py
topik/visualizers/pyldavis.py
topik/visualizers/termite_plot.py
topik/visualizers/tests/__init__.py
topik/visualizers/tests/test_ldavis.py
topik-0.3.0.dist-info/DESCRIPTION.rst
topik-0.3.0.dist-info/METADATA
topik-0.3.0.dist-info/RECORD
topik-0.3.0.dist-info/WHEEL
topik-0.3.0.dist-info/entry_points.txt
topik-0.3.0.dist-info/metadata.json
topik-0.3.0.dist-info/pbr.json
topik-0.3.0.dist-info/top_level.txt
