Metadata-Version: 2.0
Name: topik
Version: 0.3.0
Summary: A Topic Modeling toolkit
Home-page: http://github.com/ContinuumIO/topik/
Author: Topik development team
Author-email: msarahan@continuum.io
License: BSD
Keywords: topic modeling lda nltk gensim pattern
Platform: UNKNOWN
Requires-Dist: blaze
Requires-Dist: bokeh
Requires-Dist: click
Requires-Dist: elasticsearch
Requires-Dist: gensim
Requires-Dist: ijson
Requires-Dist: jsonpickle
Requires-Dist: nltk
Requires-Dist: numpy
Requires-Dist: odo
Requires-Dist: pandas
Requires-Dist: pattern
Requires-Dist: pattern
Requires-Dist: setuptools-markdown
Requires-Dist: textblob
Requires-Dist: versioneer
